ChengweiZhuanyeTaluoshiNigaiShenrudeZhanbuMiji/README.md
ChengweiZhuanyeTaluoshiNigaiShenrudeZhanbuMiji/__init__.py
ChengweiZhuanyeTaluoshiNigaiShenrudeZhanbuMiji/__main__.py
ChengweiZhuanyeTaluoshiNigaiShenrudeZhanbuMiji/file.epub
ChengweiZhuanyeTaluoshiNigaiShenrudeZhanbuMiji/index.html
ChengweiZhuanyeTaluoshiNigaiShenrudeZhanbuMiji/css/__init__.py
ChengweiZhuanyeTaluoshiNigaiShenrudeZhanbuMiji/css/annotations.css
ChengweiZhuanyeTaluoshiNigaiShenrudeZhanbuMiji/css/main.css
ChengweiZhuanyeTaluoshiNigaiShenrudeZhanbuMiji/css/normalize.css
ChengweiZhuanyeTaluoshiNigaiShenrudeZhanbuMiji/css/popup.css
ChengweiZhuanyeTaluoshiNigaiShenrudeZhanbuMiji/font/__init__.py
ChengweiZhuanyeTaluoshiNigaiShenrudeZhanbuMiji/font/fontello.eot
ChengweiZhuanyeTaluoshiNigaiShenrudeZhanbuMiji/font/fontello.svg
ChengweiZhuanyeTaluoshiNigaiShenrudeZhanbuMiji/font/fontello.ttf
ChengweiZhuanyeTaluoshiNigaiShenrudeZhanbuMiji/font/fontello.woff
ChengweiZhuanyeTaluoshiNigaiShenrudeZhanbuMiji/img/__init__.py
ChengweiZhuanyeTaluoshiNigaiShenrudeZhanbuMiji/img/annotator-glyph-sprite.png
ChengweiZhuanyeTaluoshiNigaiShenrudeZhanbuMiji/img/annotator-icon-sprite.png
ChengweiZhuanyeTaluoshiNigaiShenrudeZhanbuMiji/img/apple-touch-icon.png
ChengweiZhuanyeTaluoshiNigaiShenrudeZhanbuMiji/img/cancelfullscreen.png
ChengweiZhuanyeTaluoshiNigaiShenrudeZhanbuMiji/img/close.png
ChengweiZhuanyeTaluoshiNigaiShenrudeZhanbuMiji/img/fullscreen.png
ChengweiZhuanyeTaluoshiNigaiShenrudeZhanbuMiji/img/loader.gif
ChengweiZhuanyeTaluoshiNigaiShenrudeZhanbuMiji/img/menu-icon.png
ChengweiZhuanyeTaluoshiNigaiShenrudeZhanbuMiji/img/save.png
ChengweiZhuanyeTaluoshiNigaiShenrudeZhanbuMiji/img/saved.png
ChengweiZhuanyeTaluoshiNigaiShenrudeZhanbuMiji/img/settings-s.png
ChengweiZhuanyeTaluoshiNigaiShenrudeZhanbuMiji/img/settings.png
ChengweiZhuanyeTaluoshiNigaiShenrudeZhanbuMiji/img/star.png
ChengweiZhuanyeTaluoshiNigaiShenrudeZhanbuMiji/js/__init__.py
ChengweiZhuanyeTaluoshiNigaiShenrudeZhanbuMiji/js/epub.js
chengwei_zhuanye_taluoshi_nigai_shenrude_zhanbu_miji-2022.9.29.0.dist-info/METADATA
chengwei_zhuanye_taluoshi_nigai_shenrude_zhanbu_miji-2022.9.29.0.dist-info/WHEEL
chengwei_zhuanye_taluoshi_nigai_shenrude_zhanbu_miji-2022.9.29.0.dist-info/entry_points.txt
chengwei_zhuanye_taluoshi_nigai_shenrude_zhanbu_miji-2022.9.29.0.dist-info/top_level.txt
chengwei_zhuanye_taluoshi_nigai_shenrude_zhanbu_miji-2022.9.29.0.dist-info/RECORD
